naga_abc/__init__.py
naga_abc/__main__.py
naga_abc/names.txt
naga_abc/speaker.py
naga_abc/speakers/__init__.py
naga_abc/speakers/justin.py
naga_abc-0.3.0.dist-info/licenses/LICENSE.txt
naga_abc-0.3.0.dist-info/METADATA
naga_abc-0.3.0.dist-info/WHEEL
naga_abc-0.3.0.dist-info/entry_points.txt
naga_abc-0.3.0.dist-info/top_level.txt
naga_abc-0.3.0.dist-info/RECORD
