Metadata-Version: 2.4
Name: naga_abc
Version: 0.3.0
Summary: My first package!
Author-email: naga n <naga.n.test.2@gmail.com>
Maintainer-email: naga n <naga.n.test.2@gmail.com>
License: Copyright 2025 Naga Nandyala
Project-URL: Homepage, https://github.com/naga-nandyala/naga_abc
Project-URL: Documentation, https://github.com/naga-nandyala/naga_abc/README.md
Keywords: naga_abc
Classifier: Programming Language :: Python :: 3.11
Classifier: Programming Language :: Python :: Implementation :: CPython
Classifier: License :: OSI Approved :: BSD License
Classifier: Intended Audience :: Developers
Classifier: Operating System :: POSIX :: Linux
Classifier: Operating System :: Microsoft :: Windows
Classifier: Operating System :: MacOS
Classifier: Operating System :: MacOS :: MacOS X
Requires-Python: >=3.11
License-File: LICENSE.txt
Requires-Dist: colorama~=0.0
Provides-Extra: dev
Requires-Dist: twine; extra == "dev"
Requires-Dist: build; extra == "dev"
Dynamic: license-file
